lambdasdk/__init__.py
lambdasdk/_nbdev.py
lambdasdk/lambdasdk.py
lambdasdk-0.1.4.dist-info/LICENSE
lambdasdk-0.1.4.dist-info/METADATA
lambdasdk-0.1.4.dist-info/WHEEL
lambdasdk-0.1.4.dist-info/entry_points.txt
lambdasdk-0.1.4.dist-info/top_level.txt
lambdasdk-0.1.4.dist-info/RECORD
