Metadata-Version: 2.1
Name: lambdasdk
Version: 0.1.4
Summary: for invoking aws lambda functions
Home-page: https://github.com/thanakijwanavit/lambdasdk
Author: Nic
Author-email: nwanavit@hatari.cc
License: Apache Software License 2.0
Keywords: lambdasdk
Platform: UNKNOWN
Classifier: Development Status :: 3 - Alpha
Classifier: Intended Audience :: Developers
Classifier: License :: OSI Approved :: Apache Software License
Classifier: Natural Language :: English
Classifier: Programming Language :: Python :: 3.6
Classifier: Programming Language :: Python :: 3.7
Classifier: Programming Language :: Python :: 3.8
Requires-Python: >=3.6
